giradischi/__init__.py
giradischi/__main__.py
giradischi/backends/__init__.py
giradischi/backends/base.py
giradischi/main.py
giradischi/ui/__init__.py
giradischi/ui/backend_selector_dialog.ui
giradischi/ui/backend_settings_dialog.ui
giradischi/ui/mainwindow.ui
giradischi/utils/midi_player.py
giradischi-1.1.0.dist-info/entry_points.txt
giradischi-1.1.0.dist-info/WHEEL
giradischi-1.1.0.dist-info/METADATA
giradischi-1.1.0.dist-info/RECORD
