Metadata-Version: 2.1
Name: giradischi
Version: 1.1.0
Summary: GUI MIDI player supporting multiple backends
Home-page: https://github.com/SebaUbuntu/giradischi
License: LGPL-3.0-or-later
Author: Sebastiano Barezzi
Author-email: barezzisebastiano@gmail.com
Requires-Python: >=3.8,<3.11
Classifier: License :: OSI Approved :: GNU Lesser General Public License v3 or later (LGPLv3+)
Classifier: Programming Language :: Python :: 3
Classifier: Programming Language :: Python :: 3.10
Classifier: Programming Language :: Python :: 3.8
Classifier: Programming Language :: Python :: 3.9
Requires-Dist: PySide6 (>=6.2.4,<7.0.0)
Requires-Dist: libmidi (>=1.0.1,<2.0.0)
Requires-Dist: libmidi-io (>=1.0.1,<2.0.0)
Project-URL: Repository, https://github.com/SebaUbuntu/giradischi
